cliff/Application.py
cliff/__init__.py
cliff/helpers.py
cliff/Commands/ListCommand.py
cliff/Commands/PrintCommands.py
cliff/Commands/PrintOptions.py
cliff/Commands/__init__.py
cliff/Options/VersionOption.py
cliff/Options/__init__.py
cliff/Support/Repository.py
cliff/Support/__init__.py
cliff_wyattcast44-0.0.1.dist-info/LICENSE.md
cliff_wyattcast44-0.0.1.dist-info/METADATA
cliff_wyattcast44-0.0.1.dist-info/WHEEL
cliff_wyattcast44-0.0.1.dist-info/top_level.txt
cliff_wyattcast44-0.0.1.dist-info/RECORD
