Metadata-Version: 2.1
Name: cliff-wyattcast44
Version: 0.0.1
Summary: A framework for building command line applications
Home-page: https://github.com/wyattcast44/CLIFF
Author: Wyatt Castaneda
Author-email: wyatt.castaneda@gmail.com
License: UNKNOWN
Platform: UNKNOWN
Classifier: Programming Language :: Python :: 3
Classifier: License :: OSI Approved :: MIT License
Classifier: Operating System :: OS Independent
Requires-Python: >=3.6
